test/test_all.py
docs/_utils/convert_docstrings.py
docs/images/wisdem/make_xdsm.py
docs/scripts/latex-fix.py
docs/scripts/custom-fix.py
docs/docstrings/get_docstrings.py
docs/docstrings/update_variable_guides.py
wisdem/__init__.py
wisdem/meson.build
wisdem/main.py
wisdem/glue_code/gc_RunTools.py
wisdem/glue_code/glue_code.py
wisdem/glue_code/__init__.py
wisdem/glue_code/gc_WT_DataStruc.py
wisdem/glue_code/gc_WT_InitModel.py
wisdem/glue_code/runWISDEM.py
wisdem/glue_code/gc_PoseOptimization.py
wisdem/glue_code/gc_LoadInputs.py
wisdem/precomp/properties.py
wisdem/precomp/profile.py
wisdem/precomp/__init__.py
wisdem/precomp/meson.build.precomp
wisdem/precomp/precomp.py
wisdem/precomp/orthotropic.py
wisdem/precomp/precomp_to_beamdyn.py
wisdem/precomp/writer.py
wisdem/precomp/composite_section.py
wisdem/ccblade/Polar.py
wisdem/ccblade/_bem.cpython-312-darwin.so
wisdem/ccblade/polar_file.py
wisdem/ccblade/__init__.py
wisdem/ccblade/_bem.cpython-39-darwin.so
wisdem/ccblade/meson.build
wisdem/ccblade/_bem.cpython-311-darwin.so
wisdem/ccblade/_bem.cpython-310-darwin.so
wisdem/ccblade/ccblade.py
wisdem/ccblade/ccblade_component.py
wisdem/orbit/__init__.py
wisdem/orbit/orbit_api.py
wisdem/towerse/__init__.py
wisdem/towerse/tower.py
wisdem/plant_financese/__init__.py
wisdem/plant_financese/plant_finance.py
wisdem/optimization_drivers/intermittent_component.py
wisdem/optimization_drivers/dakota_driver.py
wisdem/optimization_drivers/nlopt_driver.py
wisdem/optimization_drivers/nsga2_driver.py
wisdem/optimization_drivers/__init__.py
wisdem/optimization_drivers/nsga2/fast_nondom_sort.py
wisdem/optimization_drivers/nsga2/crowding_distance_assignment.py
wisdem/optimization_drivers/nsga2/algo_nsga2.py
wisdem/optimization_drivers/nsga2/genetic_functions.py
wisdem/nrelcsm/csmPPI.py
wisdem/nrelcsm/__init__.py
wisdem/nrelcsm/nrel_csm_orig.py
wisdem/nrelcsm/nrel_csm_mass_2015.py
wisdem/nrelcsm/nrel_csm_cost_2015.py
meson_build/meson-info/meson-info.json
wisdem-4.0.5.dist-info/RECORD
wisdem-4.0.5.dist-info/WHEEL
wisdem-4.0.5.dist-info/entry_points.txt
wisdem-4.0.5.dist-info/top_level.txt
wisdem-4.0.5.dist-info/METADATA
wisdem-4.0.5.dist-info/licenses/LICENSE
wisdem-4.0.5.dist-info/licenses/NOTICE
