Metadata-Version: 2.4
Name: wisdem
Version: 4.0.5
Summary: Wind-Plant Integrated System Design & Engineering Model
Author-email: NREL WISDEM Team <systems.engineering@nrel.gov>
Maintainer-email: NREL WISDEM Team <systems.engineering@nrel.gov>
License: Apache-2.0
Project-URL: Homepage, https://github.com/WISDEM/WISDEM
Project-URL: Documentation, https://wisdem.readthedocs.io
Project-URL: Project, https://www.nrel.gov/wind/systems-engineering.html
Keywords: wind,turbine,mdao,design,optimization
Classifier: Development Status :: 4 - Beta
Classifier: Intended Audience :: Science/Research
Classifier: Topic :: Scientific/Engineering
Classifier: License :: OSI Approved :: Apache Software License
Classifier: Programming Language :: Python :: 3
Classifier: Programming Language :: Python :: 3.9
Classifier: Programming Language :: Python :: 3.10
Classifier: Programming Language :: Python :: 3.11
Classifier: Programming Language :: Python :: 3.12
Classifier: Programming Language :: Python :: 3.13
Classifier: Programming Language :: Python :: 3.14
Classifier: Programming Language :: Python :: 3 :: Only
Classifier: Programming Language :: C
Classifier: Programming Language :: Fortran
Classifier: Operating System :: Microsoft :: Windows
Classifier: Operating System :: POSIX :: Linux
Classifier: Operating System :: POSIX
Classifier: Operating System :: Unix
Classifier: Operating System :: MacOS
Requires-Python: >=3.9
License-File: LICENSE
License-File: NOTICE
Requires-Dist: jsonmerge
Requires-Dist: jsonschema
Requires-Dist: moorpy>=1.2
Requires-Dist: numpy
Requires-Dist: openmdao
Requires-Dist: openpyxl
Requires-Dist: orbit-nrel>=1.2.1
Requires-Dist: pandas
Requires-Dist: pydoe3
Requires-Dist: pyyaml
Requires-Dist: scipy
Requires-Dist: sortedcontainers
Requires-Dist: statsmodels>=0.14.5
Requires-Dist: windIO
Provides-Extra: dev
Requires-Dist: meson; extra == "dev"
Requires-Dist: ninja; extra == "dev"
Requires-Dist: swig; extra == "dev"
Requires-Dist: black; extra == "dev"
Requires-Dist: pre-commit; extra == "dev"
Requires-Dist: isort; extra == "dev"
Provides-Extra: test
Requires-Dist: coveralls; extra == "test"
Requires-Dist: pytest; extra == "test"
Requires-Dist: pytest-cov; extra == "test"
Provides-Extra: gui
Requires-Dist: dearpygui; extra == "gui"
Provides-Extra: docs
Requires-Dist: sphinx; extra == "docs"
Requires-Dist: sphinxcontrib-bibtex; extra == "docs"
Requires-Dist: sphinx_rtd_theme>=1.3; extra == "docs"
Requires-Dist: sphinx-jsonschema; extra == "docs"
Requires-Dist: sphinx-copybutton; extra == "docs"
Requires-Dist: numpydoc; extra == "docs"
Provides-Extra: opt
Requires-Dist: pyoptsparse; extra == "opt"
Requires-Dist: nlopt; extra == "opt"
Dynamic: license-file
